{
  "actuaciones": [
    {
      "idRegActuacion": 903204510,
      "llaveProceso": "11001400302420180011900",
      "consActuacion": 35,
      "fechaActuacion": "2019-12-10T05:00:00.000Z",
      "actuacion": "Recepción memorial",
      "anotacion": null,
      "fechaInicial": null,
      "fechaFinal": null,
      "fechaRegistro": "2019-12-10T05:00:00.000Z",
      "codRegla": "00                              ",
      "conDocumentos": false,
      "cant": 35,
      "idProceso": 50990990,
      "isUltimaAct": true,
      "carpetaNumero": 109,
      "createdAt": "2023-12-10T20:30:38.029Z"
    },
    {
      "idRegActuacion": 565010490,
      "llaveProceso": "11001400302420180011900",
      "consActuacion": 34,
      "fechaActuacion": "2019-09-27T05:00:00.000Z",
      "actuacion": "Reactiva Proceso",
      "anotacion": null,
      "fechaInicial": null,
      "fechaFinal": null,
      "fechaRegistro": "2019-09-27T05:00:00.000Z",
      "codRegla": "00                              ",
      "conDocumentos": false,
      "cant": 35,
      "idProceso": 50990990,
      "isUltimaAct": false,
      "carpetaNumero": 109,
      "createdAt": "2023-12-10T20:30:38.029Z"
    },
    {
      "idRegActuacion": 557362330,
      "llaveProceso": "11001400302420180011900",
      "consActuacion": 33,
      "fechaActuacion": "2019-04-26T05:00:00.000Z",
      "actuacion": "Archivo Definitivo",
      "anotacion": "ARCHIVO TUTELAS 2019 CAJA 489 26 DE ABRIL DE 2019",
      "fechaInicial": null,
      "fechaFinal": null,
      "fechaRegistro": "2019-06-07T05:00:00.000Z",
      "codRegla": "00                              ",
      "conDocumentos": false,
      "cant": 35,
      "idProceso": 50990990,
      "isUltimaAct": false,
      "carpetaNumero": 109,
      "createdAt": "2023-12-10T20:30:38.029Z"
    },
    {
      "idRegActuacion": 557362320,
      "llaveProceso": "11001400302420180011900",
      "consActuacion": 32,
      "fechaActuacion": "2019-02-12T05:00:00.000Z",
      "actuacion": "Recepción memorial",
      "anotacion": "TRANSITO LEVANTA MEDIDA",
      "fechaInicial": null,
      "fechaFinal": null,
      "fechaRegistro": "2019-02-12T05:00:00.000Z",
      "codRegla": "00                              ",
      "conDocumentos": false,
      "cant": 35,
      "idProceso": 50990990,
      "isUltimaAct": false,
      "carpetaNumero": 109,
      "createdAt": "2023-12-10T20:30:38.029Z"
    },
    {
      "idRegActuacion": 557362310,
      "llaveProceso": "11001400302420180011900",
      "consActuacion": 31,
      "fechaActuacion": "2018-09-28T05:00:00.000Z",
      "actuacion": "Oficio Elaborado",
      "anotacion": null,
      "fechaInicial": null,
      "fechaFinal": null,
      "fechaRegistro": "2019-01-22T05:00:00.000Z",
      "codRegla": "00                              ",
      "conDocumentos": false,
      "cant": 35,
      "idProceso": 50990990,
      "isUltimaAct": false,
      "carpetaNumero": 109,
      "createdAt": "2023-12-10T20:30:38.029Z"
    },
    {
      "idRegActuacion": 557362300,
      "llaveProceso": "11001400302420180011900",
      "consActuacion": 30,
      "fechaActuacion": "2018-09-17T05:00:00.000Z",
      "actuacion": "Fijacion estado",
      "anotacion": "Actuación registrada el 17/09/2018 a las 18:56:41.",
      "fechaInicial": "2018-09-18T05:00:00.000Z",
      "fechaFinal": "2018-09-18T05:00:00.000Z",
      "fechaRegistro": "2018-09-17T05:00:00.000Z",
      "codRegla": "00                              ",
      "conDocumentos": false,
      "cant": 35,
      "idProceso": 50990990,
      "isUltimaAct": false,
      "carpetaNumero": 109,
      "createdAt": "2023-12-10T20:30:38.029Z"
    },
    {
      "idRegActuacion": 557362290,
      "llaveProceso": "11001400302420180011900",
      "consActuacion": 29,
      "fechaActuacion": "2018-09-17T05:00:00.000Z",
      "actuacion": "Auto termina proceso por Pago",
      "anotacion": null,
      "fechaInicial": null,
      "fechaFinal": null,
      "fechaRegistro": "2018-09-17T05:00:00.000Z",
      "codRegla": "00                              ",
      "conDocumentos": false,
      "cant": 35,
      "idProceso": 50990990,
      "isUltimaAct": false,
      "carpetaNumero": 109,
      "createdAt": "2023-12-10T20:30:38.029Z"
    },
    {
      "idRegActuacion": 557362280,
      "llaveProceso": "11001400302420180011900",
      "consActuacion": 28,
      "fechaActuacion": "2018-09-04T05:00:00.000Z",
      "actuacion": "Al despacho",
      "anotacion": null,
      "fechaInicial": null,
      "fechaFinal": null,
      "fechaRegistro": "2018-09-04T05:00:00.000Z",
      "codRegla": "00                              ",
      "conDocumentos": false,
      "cant": 35,
      "idProceso": 50990990,
      "isUltimaAct": false,
      "carpetaNumero": 109,
      "createdAt": "2023-12-10T20:30:38.029Z"
    },
    {
      "idRegActuacion": 557362270,
      "llaveProceso": "11001400302420180011900",
      "consActuacion": 27,
      "fechaActuacion": "2018-09-03T05:00:00.000Z",
      "actuacion": "Recepción memorial",
      "anotacion": "SOLICITA TERMINACIÓN POR PAGO DE CUOTAS EN MORA ",
      "fechaInicial": null,
      "fechaFinal": null,
      "fechaRegistro": "2018-09-03T05:00:00.000Z",
      "codRegla": "00                              ",
      "conDocumentos": false,
      "cant": 35,
      "idProceso": 50990990,
      "isUltimaAct": false,
      "carpetaNumero": 109,
      "createdAt": "2023-12-10T20:30:38.029Z"
    },
    {
      "idRegActuacion": 557362260,
      "llaveProceso": "11001400302420180011900",
      "consActuacion": 26,
      "fechaActuacion": "2018-08-17T05:00:00.000Z",
      "actuacion": "Oficio Elaborado",
      "anotacion": null,
      "fechaInicial": null,
      "fechaFinal": null,
      "fechaRegistro": "2018-08-17T05:00:00.000Z",
      "codRegla": "00                              ",
      "conDocumentos": false,
      "cant": 35,
      "idProceso": 50990990,
      "isUltimaAct": false,
      "carpetaNumero": 109,
      "createdAt": "2023-12-10T20:30:38.029Z"
    },
    {
      "idRegActuacion": 557362250,
      "llaveProceso": "11001400302420180011900",
      "consActuacion": 25,
      "fechaActuacion": "2018-08-10T05:00:00.000Z",
      "actuacion": "Fijacion estado",
      "anotacion": "Actuación registrada el 10/08/2018 a las 19:12:17.",
      "fechaInicial": "2018-08-13T05:00:00.000Z",
      "fechaFinal": "2018-08-13T05:00:00.000Z",
      "fechaRegistro": "2018-08-10T05:00:00.000Z",
      "codRegla": "00                              ",
      "conDocumentos": false,
      "cant": 35,
      "idProceso": 50990990,
      "isUltimaAct": false,
      "carpetaNumero": 109,
      "createdAt": "2023-12-10T20:30:38.029Z"
    },
    {
      "idRegActuacion": 557362240,
      "llaveProceso": "11001400302420180011900",
      "consActuacion": 24,
      "fechaActuacion": "2018-08-10T05:00:00.000Z",
      "actuacion": "Auto ordena comisión",
      "anotacion": null,
      "fechaInicial": null,
      "fechaFinal": null,
      "fechaRegistro": "2018-08-10T05:00:00.000Z",
      "codRegla": "00                              ",
      "conDocumentos": false,
      "cant": 35,
      "idProceso": 50990990,
      "isUltimaAct": false,
      "carpetaNumero": 109,
      "createdAt": "2023-12-10T20:30:38.029Z"
    },
    {
      "idRegActuacion": 557362230,
      "llaveProceso": "11001400302420180011900",
      "consActuacion": 23,
      "fechaActuacion": "2018-08-10T05:00:00.000Z",
      "actuacion": "Fijacion estado",
      "anotacion": "Actuación registrada el 10/08/2018 a las 19:12:06.",
      "fechaInicial": "2018-08-13T05:00:00.000Z",
      "fechaFinal": "2018-08-13T05:00:00.000Z",
      "fechaRegistro": "2018-08-10T05:00:00.000Z",
      "codRegla": "00                              ",
      "conDocumentos": false,
      "cant": 35,
      "idProceso": 50990990,
      "isUltimaAct": false,
      "carpetaNumero": 109,
      "createdAt": "2023-12-10T20:30:38.029Z"
    },
    {
      "idRegActuacion": 557362220,
      "llaveProceso": "11001400302420180011900",
      "consActuacion": 22,
      "fechaActuacion": "2018-08-10T05:00:00.000Z",
      "actuacion": "Auto fija fecha audiencia y/o diligencia",
      "anotacion": null,
      "fechaInicial": null,
      "fechaFinal": null,
      "fechaRegistro": "2018-08-10T05:00:00.000Z",
      "codRegla": "00                              ",
      "conDocumentos": false,
      "cant": 35,
      "idProceso": 50990990,
      "isUltimaAct": false,
      "carpetaNumero": 109,
      "createdAt": "2023-12-10T20:30:38.029Z"
    },
    {
      "idRegActuacion": 557362210,
      "llaveProceso": "11001400302420180011900",
      "consActuacion": 21,
      "fechaActuacion": "2018-07-30T05:00:00.000Z",
      "actuacion": "Al despacho",
      "anotacion": null,
      "fechaInicial": null,
      "fechaFinal": null,
      "fechaRegistro": "2018-07-30T05:00:00.000Z",
      "codRegla": "00                              ",
      "conDocumentos": false,
      "cant": 35,
      "idProceso": 50990990,
      "isUltimaAct": false,
      "carpetaNumero": 109,
      "createdAt": "2023-12-10T20:30:38.029Z"
    },
    {
      "idRegActuacion": 557362200,
      "llaveProceso": "11001400302420180011900",
      "consActuacion": 20,
      "fechaActuacion": "2018-07-26T05:00:00.000Z",
      "actuacion": "Recepción memorial",
      "anotacion": "SOLICITA CAPTURA VEHÍCULO",
      "fechaInicial": null,
      "fechaFinal": null,
      "fechaRegistro": "2018-07-26T05:00:00.000Z",
      "codRegla": "00                              ",
      "conDocumentos": false,
      "cant": 35,
      "idProceso": 50990990,
      "isUltimaAct": false,
      "carpetaNumero": 109,
      "createdAt": "2023-12-10T20:30:38.029Z"
    },
    {
      "idRegActuacion": 557362190,
      "llaveProceso": "11001400302420180011900",
      "consActuacion": 19,
      "fechaActuacion": "2018-07-12T05:00:00.000Z",
      "actuacion": "Recepción memorial",
      "anotacion": null,
      "fechaInicial": null,
      "fechaFinal": null,
      "fechaRegistro": "2018-07-12T05:00:00.000Z",
      "codRegla": "00                              ",
      "conDocumentos": false,
      "cant": 35,
      "idProceso": 50990990,
      "isUltimaAct": false,
      "carpetaNumero": 109,
      "createdAt": "2023-12-10T20:30:38.029Z"
    },
    {
      "idRegActuacion": 557362180,
      "llaveProceso": "11001400302420180011900",
      "consActuacion": 18,
      "fechaActuacion": "2018-07-09T05:00:00.000Z",
      "actuacion": "Fijacion estado",
      "anotacion": "Actuación registrada el 09/07/2018 a las 17:14:13.",
      "fechaInicial": "2018-07-10T05:00:00.000Z",
      "fechaFinal": "2018-07-10T05:00:00.000Z",
      "fechaRegistro": "2018-07-09T05:00:00.000Z",
      "codRegla": "00                              ",
      "conDocumentos": false,
      "cant": 35,
      "idProceso": 50990990,
      "isUltimaAct": false,
      "carpetaNumero": 109,
      "createdAt": "2023-12-10T20:30:38.029Z"
    },
    {
      "idRegActuacion": 557362170,
      "llaveProceso": "11001400302420180011900",
      "consActuacion": 17,
      "fechaActuacion": "2018-07-09T05:00:00.000Z",
      "actuacion": "Requiere So Pena Articulo 317 C.G.P",
      "anotacion": null,
      "fechaInicial": null,
      "fechaFinal": null,
      "fechaRegistro": "2018-07-09T05:00:00.000Z",
      "codRegla": "00                              ",
      "conDocumentos": false,
      "cant": 35,
      "idProceso": 50990990,
      "isUltimaAct": false,
      "carpetaNumero": 109,
      "createdAt": "2023-12-10T20:30:38.029Z"
    },
    {
      "idRegActuacion": 557362160,
      "llaveProceso": "11001400302420180011900",
      "consActuacion": 16,
      "fechaActuacion": "2018-06-25T05:00:00.000Z",
      "actuacion": "Al despacho",
      "anotacion": null,
      "fechaInicial": null,
      "fechaFinal": null,
      "fechaRegistro": "2018-06-25T05:00:00.000Z",
      "codRegla": "00                              ",
      "conDocumentos": false,
      "cant": 35,
      "idProceso": 50990990,
      "isUltimaAct": false,
      "carpetaNumero": 109,
      "createdAt": "2023-12-10T20:30:38.029Z"
    },
    {
      "idRegActuacion": 557362150,
      "llaveProceso": "11001400302420180011900",
      "consActuacion": 15,
      "fechaActuacion": "2018-06-19T05:00:00.000Z",
      "actuacion": "Recepción memorial",
      "anotacion": null,
      "fechaInicial": null,
      "fechaFinal": null,
      "fechaRegistro": "2018-06-19T05:00:00.000Z",
      "codRegla": "00                              ",
      "conDocumentos": false,
      "cant": 35,
      "idProceso": 50990990,
      "isUltimaAct": false,
      "carpetaNumero": 109,
      "createdAt": "2023-12-10T20:30:38.029Z"
    },
    {
      "idRegActuacion": 557362140,
      "llaveProceso": "11001400302420180011900",
      "consActuacion": 14,
      "fechaActuacion": "2018-06-05T05:00:00.000Z",
      "actuacion": "Fijacion estado",
      "anotacion": "Actuación registrada el 05/06/2018 a las 19:07:22.",
      "fechaInicial": "2018-06-06T05:00:00.000Z",
      "fechaFinal": "2018-06-06T05:00:00.000Z",
      "fechaRegistro": "2018-06-05T05:00:00.000Z",
      "codRegla": "00                              ",
      "conDocumentos": false,
      "cant": 35,
      "idProceso": 50990990,
      "isUltimaAct": false,
      "carpetaNumero": 109,
      "createdAt": "2023-12-10T20:30:38.029Z"
    },
    {
      "idRegActuacion": 557362130,
      "llaveProceso": "11001400302420180011900",
      "consActuacion": 13,
      "fechaActuacion": "2018-06-05T05:00:00.000Z",
      "actuacion": "Auto requiere",
      "anotacion": null,
      "fechaInicial": null,
      "fechaFinal": null,
      "fechaRegistro": "2018-06-05T05:00:00.000Z",
      "codRegla": "00                              ",
      "conDocumentos": false,
      "cant": 35,
      "idProceso": 50990990,
      "isUltimaAct": false,
      "carpetaNumero": 109,
      "createdAt": "2023-12-10T20:30:38.029Z"
    },
    {
      "idRegActuacion": 557362120,
      "llaveProceso": "11001400302420180011900",
      "consActuacion": 12,
      "fechaActuacion": "2018-05-24T05:00:00.000Z",
      "actuacion": "Al despacho",
      "anotacion": null,
      "fechaInicial": null,
      "fechaFinal": null,
      "fechaRegistro": "2018-05-24T05:00:00.000Z",
      "codRegla": "00                              ",
      "conDocumentos": false,
      "cant": 35,
      "idProceso": 50990990,
      "isUltimaAct": false,
      "carpetaNumero": 109,
      "createdAt": "2023-12-10T20:30:38.029Z"
    },
    {
      "idRegActuacion": 557362110,
      "llaveProceso": "11001400302420180011900",
      "consActuacion": 11,
      "fechaActuacion": "2018-05-08T05:00:00.000Z",
      "actuacion": "Diligencia de notificación personal (acta)",
      "anotacion": "SE NOTIFICA DEMANDADO",
      "fechaInicial": null,
      "fechaFinal": null,
      "fechaRegistro": "2018-05-08T05:00:00.000Z",
      "codRegla": "00                              ",
      "conDocumentos": false,
      "cant": 35,
      "idProceso": 50990990,
      "isUltimaAct": false,
      "carpetaNumero": 109,
      "createdAt": "2023-12-10T20:30:38.029Z"
    },
    {
      "idRegActuacion": 557362100,
      "llaveProceso": "11001400302420180011900",
      "consActuacion": 10,
      "fechaActuacion": "2018-04-13T05:00:00.000Z",
      "actuacion": "Oficio Elaborado",
      "anotacion": "EMBARGO VEHICULO",
      "fechaInicial": null,
      "fechaFinal": null,
      "fechaRegistro": "2018-04-13T05:00:00.000Z",
      "codRegla": "00                              ",
      "conDocumentos": false,
      "cant": 35,
      "idProceso": 50990990,
      "isUltimaAct": false,
      "carpetaNumero": 109,
      "createdAt": "2023-12-10T20:30:38.029Z"
    },
    {
      "idRegActuacion": 557362090,
      "llaveProceso": "11001400302420180011900",
      "consActuacion": 9,
      "fechaActuacion": "2018-04-03T05:00:00.000Z",
      "actuacion": "Fijacion estado",
      "anotacion": "Actuación registrada el 03/04/2018 a las 17:29:41.",
      "fechaInicial": "2018-04-04T05:00:00.000Z",
      "fechaFinal": "2018-04-04T05:00:00.000Z",
      "fechaRegistro": "2018-04-03T05:00:00.000Z",
      "codRegla": "00                              ",
      "conDocumentos": false,
      "cant": 35,
      "idProceso": 50990990,
      "isUltimaAct": false,
      "carpetaNumero": 109,
      "createdAt": "2023-12-10T20:30:38.029Z"
    },
    {
      "idRegActuacion": 557362080,
      "llaveProceso": "11001400302420180011900",
      "consActuacion": 8,
      "fechaActuacion": "2018-04-03T05:00:00.000Z",
      "actuacion": "Auto libra mandamiento ejecutivo",
      "anotacion": null,
      "fechaInicial": null,
      "fechaFinal": null,
      "fechaRegistro": "2018-04-03T05:00:00.000Z",
      "codRegla": "00                              ",
      "conDocumentos": false,
      "cant": 35,
      "idProceso": 50990990,
      "isUltimaAct": false,
      "carpetaNumero": 109,
      "createdAt": "2023-12-10T20:30:38.029Z"
    },
    {
      "idRegActuacion": 557362070,
      "llaveProceso": "11001400302420180011900",
      "consActuacion": 7,
      "fechaActuacion": "2018-03-08T05:00:00.000Z",
      "actuacion": "Al despacho",
      "anotacion": null,
      "fechaInicial": null,
      "fechaFinal": null,
      "fechaRegistro": "2018-03-08T05:00:00.000Z",
      "codRegla": "00                              ",
      "conDocumentos": false,
      "cant": 35,
      "idProceso": 50990990,
      "isUltimaAct": false,
      "carpetaNumero": 109,
      "createdAt": "2023-12-10T20:30:38.029Z"
    },
    {
      "idRegActuacion": 557362060,
      "llaveProceso": "11001400302420180011900",
      "consActuacion": 6,
      "fechaActuacion": "2018-03-05T05:00:00.000Z",
      "actuacion": "Recepción memorial",
      "anotacion": null,
      "fechaInicial": null,
      "fechaFinal": null,
      "fechaRegistro": "2018-03-05T05:00:00.000Z",
      "codRegla": "00                              ",
      "conDocumentos": false,
      "cant": 35,
      "idProceso": 50990990,
      "isUltimaAct": false,
      "carpetaNumero": 109,
      "createdAt": "2023-12-10T20:30:38.029Z"
    },
    {
      "idRegActuacion": 557362050,
      "llaveProceso": "11001400302420180011900",
      "consActuacion": 5,
      "fechaActuacion": "2018-03-02T05:00:00.000Z",
      "actuacion": "Recepción memorial",
      "anotacion": null,
      "fechaInicial": null,
      "fechaFinal": null,
      "fechaRegistro": "2018-03-02T05:00:00.000Z",
      "codRegla": "00                              ",
      "conDocumentos": false,
      "cant": 35,
      "idProceso": 50990990,
      "isUltimaAct": false,
      "carpetaNumero": 109,
      "createdAt": "2023-12-10T20:30:38.029Z"
    },
    {
      "idRegActuacion": 557362040,
      "llaveProceso": "11001400302420180011900",
      "consActuacion": 4,
      "fechaActuacion": "2018-02-23T05:00:00.000Z",
      "actuacion": "Fijacion estado",
      "anotacion": "Actuación registrada el 23/02/2018 a las 17:54:33.",
      "fechaInicial": "2018-02-26T05:00:00.000Z",
      "fechaFinal": "2018-02-26T05:00:00.000Z",
      "fechaRegistro": "2018-02-23T05:00:00.000Z",
      "codRegla": "00                              ",
      "conDocumentos": false,
      "cant": 35,
      "idProceso": 50990990,
      "isUltimaAct": false,
      "carpetaNumero": 109,
      "createdAt": "2023-12-10T20:30:38.029Z"
    },
    {
      "idRegActuacion": 557362030,
      "llaveProceso": "11001400302420180011900",
      "consActuacion": 3,
      "fechaActuacion": "2018-02-23T05:00:00.000Z",
      "actuacion": "Auto inadmite demanda",
      "anotacion": null,
      "fechaInicial": null,
      "fechaFinal": null,
      "fechaRegistro": "2018-02-23T05:00:00.000Z",
      "codRegla": "00                              ",
      "conDocumentos": false,
      "cant": 35,
      "idProceso": 50990990,
      "isUltimaAct": false,
      "carpetaNumero": 109,
      "createdAt": "2023-12-10T20:30:38.029Z"
    },
    {
      "idRegActuacion": 557362020,
      "llaveProceso": "11001400302420180011900",
      "consActuacion": 2,
      "fechaActuacion": "2018-02-07T05:00:00.000Z",
      "actuacion": "Al despacho por reparto",
      "anotacion": null,
      "fechaInicial": null,
      "fechaFinal": null,
      "fechaRegistro": "2018-02-07T05:00:00.000Z",
      "codRegla": "00                              ",
      "conDocumentos": false,
      "cant": 35,
      "idProceso": 50990990,
      "isUltimaAct": false,
      "carpetaNumero": 109,
      "createdAt": "2023-12-10T20:30:38.029Z"
    },
    {
      "idRegActuacion": 557362010,
      "llaveProceso": "11001400302420180011900",
      "consActuacion": 1,
      "fechaActuacion": "2018-02-06T05:00:00.000Z",
      "actuacion": " Radicación de Proceso",
      "anotacion": "Actuación de  Radicación de Proceso  realizada el 06/02/2018 a las 18:37:49",
      "fechaInicial": "2018-02-06T05:00:00.000Z",
      "fechaFinal": "2018-02-06T05:00:00.000Z",
      "fechaRegistro": "2018-02-06T05:00:00.000Z",
      "codRegla": "00                              ",
      "conDocumentos": false,
      "cant": 35,
      "idProceso": 50990990,
      "isUltimaAct": false,
      "carpetaNumero": 109,
      "createdAt": "2023-12-10T20:30:38.029Z"
    }
  ],
  "juzgados": [
    {
      "id": 24,
      "tipo": "JUZGADO 024 CIVIL MUNICIPAL DE BOGOTÁ ",
      "url": "https://www.ramajudicial.gov.co/web/juzgado-024-civil-municipal-de-bogota"
    }
  ],
  "codeudor": null,
  "demanda": {
    "vencimientoPagare": "26/07/2017",
    "obligacion": {
      "A": 12491571
    },
    "capitalAdeudado": 21660562,
    "entregaGarantiasAbogado": "1/08/2017",
    "departamento": "CUNDINAMARCA",
    "municipio": "BOGOTA",
    "tipoProceso": "PRENDARIO",
    "radicado": "2018 - 00119",
    "llaveProceso": "11001400302420180011900",
    "etapaProcesal": "NOTIFICACION",
    "fechaPresentacion": "8/08/2017",
    "mandamientoPago": "3/04/2018",
    "notificacion": {
      "certimail": "CERTIMAIL",
      "tipo": "P/NAL",
      "autoNotificado": 43228
    },
    "medidasCautelares": {
      "fechaOrdenaMedidas": "3/04/2018",
      "medidaSolicitada": "VEHICULO"
    }
  },
  "demandas": [
    {
      "idProceso": 50990990,
      "idConexion": 259,
      "llaveProceso": "11001400302420180011900",
      "fechaProceso": "2018-02-06T05:00:00.000Z",
      "fechaUltimaActuacion": "2019-12-10T05:00:00.000Z",
      "sujetosProcesales": "Demandante: BANCOLOMBIA S.A. | Demandado: OSCAR IVAN AGUDELO MORA ",
      "esPrivado": false,
      "cantFilas": -1,
      "medidasCautelares": {
        "fechaOrdenaMedida": "2018-03-04T05:00:00.000Z",
        "medidaSolicitada": "VEHICULO"
      },
      "vencimientoPagare": ["2017-01-01T05:00:00.000Z"],
      "capitalAdeudado": 21660562,
      "departamento": "CUNDINAMARCA",
      "entregaGarantiasAbogado": "2017-01-08T05:00:00.000Z",
      "tipoProceso": "PRENDARIO",
      "mandamientoPago": "2018-03-04T05:00:00.000Z",
      "etapaProcesal": "NOTIFICACION",
      "fechaPresentacion": ["2017-08-08T05:00:00.000Z"],
      "municipio": "BOGOTA",
      "obligacion": [12491571],
      "radicado": "2018 - 00119"
    }
  ],
  "numero": 109,
  "llaveProceso": "11001400302420180011900",
  "fecha": "2019-12-10T05:00:00.000Z",
  "ultimaActuacion": {
    "idRegActuacion": 903204510,
    "llaveProceso": "11001400302420180011900",
    "consActuacion": 35,
    "fechaActuacion": "2019-12-10T00:00:00",
    "actuacion": "Recepción memorial",
    "anotacion": null,
    "fechaInicial": null,
    "fechaFinal": null,
    "fechaRegistro": "2019-12-10T00:00:00",
    "codRegla": "00                              ",
    "conDocumentos": false,
    "cant": 35,
    "idProceso": 50990990,
    "isUltimaAct": true
  },
  "category": "Terminados",
  "revisado": true,
  "terminado": true,
  "tipoProceso": "PRENDARIO",
  "deudor": {
    "tel": {
      "fijo": null,
      "celular": 3045449490
    },
    "primerNombre": "OSCAR",
    "segundoNombre": "IVAN",
    "primerApellido": "AGUDELO",
    "segundoApellido": "MORA",
    "cedula": 1018428090,
    "direccion": "CARRERA 3 D # 32A - 69 SUR",
    "email": "oscar.agudelo@crcom.gov.co"
  },
  "cc": 1018428090,
  "procesos": [
    {
      "idProceso": 50990990,
      "idConexion": 259,
      "llaveProceso": "11001400302420180011900",
      "fechaProceso": "2018-02-06T05:00:00.000Z",
      "fechaUltimaActuacion": "2019-12-10T05:00:00.000Z",
      "despacho": "JUZGADO 024 CIVIL MUNICIPAL DE BOGOTÁ ",
      "departamento": "BOGOTÁ",
      "sujetosProcesales": "Demandante: BANCOLOMBIA S.A. | Demandado: OSCAR IVAN AGUDELO MORA ",
      "esPrivado": false,
      "cantFilas": -1
    }
  ],
  "idProcesos": [50990990],
  "nombre": "OSCAR IVAN AGUDELO MORA",
  "notificacion": {
    "notifiers": [],
    "certimail": false,
    "fisico": null,
    "autoNotificado": "43228"
  }
}
