{
  "StatusCode": 400,
  "Message": "error at PrismaClientValidationError: \nInvalid `client.carpeta.upsert()` invocation in\n/home/cachorro_cami/Projects/com/rsasesorjuridico/tester/src/data/insert-carpetas.ts:77:48\n\n  74   };\n  75 }\n  76 \n→ 77 const createCarpeta = await client.carpeta.upsert({\n       where: {\n         numero: 78\n       },\n       create: {\n         numero: 78,\n         nombre: \"jaime edison santos martin\",\n         llaveProceso: \"11001400306420170123100\",\n         category: \"Terminados\",\n         idProcesos: [\n           17942390\n         ],\n         procesos: {\n           createMany: {\n             data: [\n               {\n                 idProceso: 17942390,\n                 idConexion: 260,\n                 llaveProceso: \"11001400306420170123100\",\n                 fechaProceso: \"2017-09-08T00:00:00\",\n                 fechaUltimaActuacion: \"2017-11-28T00:00:00\",\n                 despacho: \"JUZGADO 064 CIVIL MUNICIPAL DE BOGOTÁ \",\n                 departamento: \"BOGOTÁ\",\n                 sujetosProcesales: \"Demandante: BANCOLOMBIA S.A. | Demandado: JAIME EDISSON SANTOS MARTIN \",\n                 esPrivado: false,\n                 cantFilas: -1\n               }\n             ]\n           }\n         },\n         actuaciones: {\n           create: {\n             idRegActuacion: 265691570,\n             llaveProceso: \"11001400306420170123100\",\n             consActuacion: 7,\n             fechaActuacion: \"2017-11-28T00:00:00\",\n             actuacion: \"Retiro de demanada\",\n             anotacion: \"RETIRA DEMANDA DIANA PATRICIA SUAREZ AUTORIZADA DE LA DRA. MARIA HELENA SUAREZ GARCIA\",\n             fechaInicial: null,\n             fechaFinal: null,\n             fechaRegistro: \"2017-11-28T00:00:00\",\n             codRegla: \"00                              \",\n             conDocumentos: false,\n             cant: 7\n           }\n         }\n       },\n       update: {\n         numero: 78,\n         nombre: \"jaime edison santos martin\",\n         llaveProceso: \"11001400306420170123100\",\n         category: \"Terminados\",\n         idProcesos: [\n           17942390\n         ],\n         procesos: {\n           createMany: {\n             data: [\n               {\n                 idProceso: 17942390,\n                 idConexion: 260,\n                 llaveProceso: \"11001400306420170123100\",\n                 fechaProceso: \"2017-09-08T00:00:00\",\n                 fechaUltimaActuacion: \"2017-11-28T00:00:00\",\n                 despacho: \"JUZGADO 064 CIVIL MUNICIPAL DE BOGOTÁ \",\n                 departamento: \"BOGOTÁ\",\n                 sujetosProcesales: \"Demandante: BANCOLOMBIA S.A. | Demandado: JAIME EDISSON SANTOS MARTIN \",\n                 esPrivado: false,\n                 cantFilas: -1\n               }\n             ]\n           }\n         },\n         actuaciones: {\n           create: {\n             idRegActuacion: 265691570,\n             llaveProceso: \"11001400306420170123100\",\n             consActuacion: 7,\n             fechaActuacion: \"2017-11-28T00:00:00\",\n             actuacion: \"Retiro de demanada\",\n             anotacion: \"RETIRA DEMANDA DIANA PATRICIA SUAREZ AUTORIZADA DE LA DRA. MARIA HELENA SUAREZ GARCIA\",\n             fechaInicial: null,\n             fechaFinal: null,\n             fechaRegistro: \"2017-11-28T00:00:00\",\n             codRegla: \"00                              \",\n             conDocumentos: false,\n             cant: 7\n           }\n         }\n       }\n     })\n\nUnknown argument `llaveProceso`. Available options are marked with ?.",
  "data": "{\n  \"name\": \"PrismaClientValidationError\",\n  \"clientVersion\": \"5.5.2\"\n}"
}
