{
  "id": 20896387,
  "actuaciones": [
    {
      "idRegActuacion": 830631840,
      "llaveProceso": "11001400306120170079300",
      "consActuacion": 21,
      "fechaActuacion": "2018-10-17T05:00:00.000Z",
      "actuacion": "Archivo Definitivo",
      "anotacion": "347",
      "fechaInicial": null,
      "fechaFinal": null,
      "fechaRegistro": "2018-10-17T05:00:00.000Z",
      "codRegla": "00                              ",
      "conDocumentos": false,
      "cant": 21,
      "idProceso": 50655580,
      "isUltimaAct": true,
      "createdAt": "2024-01-02T02:09:32.378Z"
    },
    {
      "idRegActuacion": 830631830,
      "llaveProceso": "11001400306120170079300",
      "consActuacion": 20,
      "fechaActuacion": "2018-08-03T05:00:00.000Z",
      "actuacion": "Constancia secretarial",
      "anotacion": "Desglose",
      "fechaInicial": null,
      "fechaFinal": null,
      "fechaRegistro": "2018-08-06T05:00:00.000Z",
      "codRegla": "00                              ",
      "conDocumentos": false,
      "cant": 21,
      "idProceso": 50655580,
      "isUltimaAct": false,
      "createdAt": "2024-01-02T02:09:32.378Z"
    },
    {
      "idRegActuacion": 830631820,
      "llaveProceso": "11001400306120170079300",
      "consActuacion": 19,
      "fechaActuacion": "2018-07-11T05:00:00.000Z",
      "actuacion": "Fijacion estado",
      "anotacion": "Actuación registrada el 11/07/2018 a las 17:13:21.",
      "fechaInicial": "2018-07-12T05:00:00.000Z",
      "fechaFinal": "2018-07-12T05:00:00.000Z",
      "fechaRegistro": "2018-07-11T05:00:00.000Z",
      "codRegla": "00                              ",
      "conDocumentos": false,
      "cant": 21,
      "idProceso": 50655580,
      "isUltimaAct": false,
      "createdAt": "2024-01-02T02:09:32.378Z"
    },
    {
      "idRegActuacion": 830631810,
      "llaveProceso": "11001400306120170079300",
      "consActuacion": 18,
      "fechaActuacion": "2018-07-11T05:00:00.000Z",
      "actuacion": "Auto resuelve Solicitud",
      "anotacion": null,
      "fechaInicial": null,
      "fechaFinal": null,
      "fechaRegistro": "2018-07-11T05:00:00.000Z",
      "codRegla": "00                              ",
      "conDocumentos": false,
      "cant": 21,
      "idProceso": 50655580,
      "isUltimaAct": false,
      "createdAt": "2024-01-02T02:09:32.378Z"
    },
    {
      "idRegActuacion": 830631800,
      "llaveProceso": "11001400306120170079300",
      "consActuacion": 17,
      "fechaActuacion": "2018-06-28T05:00:00.000Z",
      "actuacion": "Al despacho",
      "anotacion": null,
      "fechaInicial": null,
      "fechaFinal": null,
      "fechaRegistro": "2018-06-28T05:00:00.000Z",
      "codRegla": "00                              ",
      "conDocumentos": false,
      "cant": 21,
      "idProceso": 50655580,
      "isUltimaAct": false,
      "createdAt": "2024-01-02T02:09:32.378Z"
    },
    {
      "idRegActuacion": 830631790,
      "llaveProceso": "11001400306120170079300",
      "consActuacion": 16,
      "fechaActuacion": "2018-06-19T05:00:00.000Z",
      "actuacion": "Recepción memorial",
      "anotacion": "un folio",
      "fechaInicial": null,
      "fechaFinal": null,
      "fechaRegistro": "2018-06-19T05:00:00.000Z",
      "codRegla": "00                              ",
      "conDocumentos": false,
      "cant": 21,
      "idProceso": 50655580,
      "isUltimaAct": false,
      "createdAt": "2024-01-02T02:09:32.378Z"
    },
    {
      "idRegActuacion": 830631780,
      "llaveProceso": "11001400306120170079300",
      "consActuacion": 15,
      "fechaActuacion": "2018-06-07T05:00:00.000Z",
      "actuacion": "Oficio Elaborado",
      "anotacion": "Of. 1069",
      "fechaInicial": null,
      "fechaFinal": null,
      "fechaRegistro": "2018-06-07T05:00:00.000Z",
      "codRegla": "00                              ",
      "conDocumentos": false,
      "cant": 21,
      "idProceso": 50655580,
      "isUltimaAct": false,
      "createdAt": "2024-01-02T02:09:32.378Z"
    },
    {
      "idRegActuacion": 830631770,
      "llaveProceso": "11001400306120170079300",
      "consActuacion": 14,
      "fechaActuacion": "2018-05-28T05:00:00.000Z",
      "actuacion": "Fijacion estado",
      "anotacion": "Actuación registrada el 28/05/2018 a las 17:19:10.",
      "fechaInicial": "2018-05-29T05:00:00.000Z",
      "fechaFinal": "2018-05-29T05:00:00.000Z",
      "fechaRegistro": "2018-05-28T05:00:00.000Z",
      "codRegla": "00                              ",
      "conDocumentos": false,
      "cant": 21,
      "idProceso": 50655580,
      "isUltimaAct": false,
      "createdAt": "2024-01-02T02:09:32.378Z"
    },
    {
      "idRegActuacion": 830631760,
      "llaveProceso": "11001400306120170079300",
      "consActuacion": 13,
      "fechaActuacion": "2018-05-28T05:00:00.000Z",
      "actuacion": "Auto termina proceso por Pago",
      "anotacion": null,
      "fechaInicial": null,
      "fechaFinal": null,
      "fechaRegistro": "2018-05-28T05:00:00.000Z",
      "codRegla": "00                              ",
      "conDocumentos": false,
      "cant": 21,
      "idProceso": 50655580,
      "isUltimaAct": false,
      "createdAt": "2024-01-02T02:09:32.378Z"
    },
    {
      "idRegActuacion": 830631750,
      "llaveProceso": "11001400306120170079300",
      "consActuacion": 12,
      "fechaActuacion": "2018-05-21T05:00:00.000Z",
      "actuacion": "Recepción memorial",
      "anotacion": null,
      "fechaInicial": null,
      "fechaFinal": null,
      "fechaRegistro": "2018-05-21T05:00:00.000Z",
      "codRegla": "00                              ",
      "conDocumentos": false,
      "cant": 21,
      "idProceso": 50655580,
      "isUltimaAct": false,
      "createdAt": "2024-01-02T02:09:32.378Z"
    },
    {
      "idRegActuacion": 830631740,
      "llaveProceso": "11001400306120170079300",
      "consActuacion": 11,
      "fechaActuacion": "2018-05-16T05:00:00.000Z",
      "actuacion": "Al despacho",
      "anotacion": null,
      "fechaInicial": null,
      "fechaFinal": null,
      "fechaRegistro": "2018-05-16T05:00:00.000Z",
      "codRegla": "00                              ",
      "conDocumentos": false,
      "cant": 21,
      "idProceso": 50655580,
      "isUltimaAct": false,
      "createdAt": "2024-01-02T02:09:32.378Z"
    },
    {
      "idRegActuacion": 830631730,
      "llaveProceso": "11001400306120170079300",
      "consActuacion": 10,
      "fechaActuacion": "2018-05-11T05:00:00.000Z",
      "actuacion": "Recepción memorial",
      "anotacion": "un folio",
      "fechaInicial": null,
      "fechaFinal": null,
      "fechaRegistro": "2018-05-11T05:00:00.000Z",
      "codRegla": "00                              ",
      "conDocumentos": false,
      "cant": 21,
      "idProceso": 50655580,
      "isUltimaAct": false,
      "createdAt": "2024-01-02T02:09:32.378Z"
    },
    {
      "idRegActuacion": 830631720,
      "llaveProceso": "11001400306120170079300",
      "consActuacion": 9,
      "fechaActuacion": "2017-10-19T05:00:00.000Z",
      "actuacion": "Oficio Elaborado",
      "anotacion": "1781",
      "fechaInicial": null,
      "fechaFinal": null,
      "fechaRegistro": "2017-10-19T05:00:00.000Z",
      "codRegla": "00                              ",
      "conDocumentos": false,
      "cant": 21,
      "idProceso": 50655580,
      "isUltimaAct": false,
      "createdAt": "2024-01-02T02:09:32.378Z"
    },
    {
      "idRegActuacion": 830631710,
      "llaveProceso": "11001400306120170079300",
      "consActuacion": 8,
      "fechaActuacion": "2017-10-03T05:00:00.000Z",
      "actuacion": "Fijacion estado",
      "anotacion": "Actuación registrada el 03/10/2017 a las 14:48:07.",
      "fechaInicial": "2017-10-04T05:00:00.000Z",
      "fechaFinal": "2017-10-04T05:00:00.000Z",
      "fechaRegistro": "2017-10-03T05:00:00.000Z",
      "codRegla": "00                              ",
      "conDocumentos": false,
      "cant": 21,
      "idProceso": 50655580,
      "isUltimaAct": false,
      "createdAt": "2024-01-02T02:09:32.378Z"
    },
    {
      "idRegActuacion": 830631700,
      "llaveProceso": "11001400306120170079300",
      "consActuacion": 7,
      "fechaActuacion": "2017-10-03T05:00:00.000Z",
      "actuacion": "Auto libra mandamiento ejecutivo",
      "anotacion": null,
      "fechaInicial": null,
      "fechaFinal": null,
      "fechaRegistro": "2017-10-03T05:00:00.000Z",
      "codRegla": "00                              ",
      "conDocumentos": false,
      "cant": 21,
      "idProceso": 50655580,
      "isUltimaAct": false,
      "createdAt": "2024-01-02T02:09:32.378Z"
    },
    {
      "idRegActuacion": 830631690,
      "llaveProceso": "11001400306120170079300",
      "consActuacion": 6,
      "fechaActuacion": "2017-09-26T05:00:00.000Z",
      "actuacion": "Al despacho",
      "anotacion": null,
      "fechaInicial": null,
      "fechaFinal": null,
      "fechaRegistro": "2017-09-26T05:00:00.000Z",
      "codRegla": "00                              ",
      "conDocumentos": false,
      "cant": 21,
      "idProceso": 50655580,
      "isUltimaAct": false,
      "createdAt": "2024-01-02T02:09:32.378Z"
    },
    {
      "idRegActuacion": 830631680,
      "llaveProceso": "11001400306120170079300",
      "consActuacion": 5,
      "fechaActuacion": "2017-09-05T05:00:00.000Z",
      "actuacion": "Recepción memorial",
      "anotacion": "subsanacion, 24 folios",
      "fechaInicial": null,
      "fechaFinal": null,
      "fechaRegistro": "2017-09-05T05:00:00.000Z",
      "codRegla": "00                              ",
      "conDocumentos": false,
      "cant": 21,
      "idProceso": 50655580,
      "isUltimaAct": false,
      "createdAt": "2024-01-02T02:09:32.378Z"
    },
    {
      "idRegActuacion": 830631670,
      "llaveProceso": "11001400306120170079300",
      "consActuacion": 4,
      "fechaActuacion": "2017-08-29T05:00:00.000Z",
      "actuacion": "Fijacion estado",
      "anotacion": "Actuación registrada el 29/08/2017 a las 16:01:54.",
      "fechaInicial": "2017-08-30T05:00:00.000Z",
      "fechaFinal": "2017-08-30T05:00:00.000Z",
      "fechaRegistro": "2017-08-29T05:00:00.000Z",
      "codRegla": "00                              ",
      "conDocumentos": false,
      "cant": 21,
      "idProceso": 50655580,
      "isUltimaAct": false,
      "createdAt": "2024-01-02T02:09:32.378Z"
    },
    {
      "idRegActuacion": 830631660,
      "llaveProceso": "11001400306120170079300",
      "consActuacion": 3,
      "fechaActuacion": "2017-08-29T05:00:00.000Z",
      "actuacion": "Auto inadmite demanda",
      "anotacion": null,
      "fechaInicial": null,
      "fechaFinal": null,
      "fechaRegistro": "2017-08-29T05:00:00.000Z",
      "codRegla": "00                              ",
      "conDocumentos": false,
      "cant": 21,
      "idProceso": 50655580,
      "isUltimaAct": false,
      "createdAt": "2024-01-02T02:09:32.378Z"
    },
    {
      "idRegActuacion": 830631650,
      "llaveProceso": "11001400306120170079300",
      "consActuacion": 2,
      "fechaActuacion": "2017-08-24T05:00:00.000Z",
      "actuacion": "Al despacho",
      "anotacion": null,
      "fechaInicial": null,
      "fechaFinal": null,
      "fechaRegistro": "2017-08-24T05:00:00.000Z",
      "codRegla": "00                              ",
      "conDocumentos": false,
      "cant": 21,
      "idProceso": 50655580,
      "isUltimaAct": false,
      "createdAt": "2024-01-02T02:09:32.378Z"
    },
    {
      "idRegActuacion": 830631640,
      "llaveProceso": "11001400306120170079300",
      "consActuacion": 1,
      "fechaActuacion": "2017-08-24T05:00:00.000Z",
      "actuacion": " Radicación de Proceso",
      "anotacion": "Actuación de  Radicación de Proceso  realizada el 24/08/2017 a las 15:07:59",
      "fechaInicial": "2017-08-24T05:00:00.000Z",
      "fechaFinal": "2017-08-24T05:00:00.000Z",
      "fechaRegistro": "2017-08-24T05:00:00.000Z",
      "codRegla": "00                              ",
      "conDocumentos": false,
      "cant": 21,
      "idProceso": 50655580,
      "isUltimaAct": false,
      "createdAt": "2024-01-02T02:09:32.378Z"
    }
  ],
  "category": "Terminados",
  "codeudor": {
    "nombre": "JOSE MARIA VILLACAMPA AINSA",
    "cedula": "18153551 DNI",
    "direccion": "CARRERA 32 # 18 - 31 SUR",
    "telefono": "3204955563",
    "id": 139
  },
  "demanda": {
    "obligacion": ["146579"],
    "llaveProceso": "11001400306120170079300",
    "notificacion": null,
    "medidasCautelares": {
      "fechaOrdenaMedida": null,
      "medidaSolicitada": "INMUEBLE"
    },
    "capitalAdeudado": null,
    "departamento": "CUNDINAMARCA",
    "despacho": null,
    "entregaGarantiasAbogado": null,
    "etapaProcesal": "NOTIFICACION",
    "fechaPresentacion": ["2017-08-23T05:00:00.000Z"],
    "mandamientoPago": null,
    "municipio": "BOGOTA",
    "radicado": "2017 - 00793",
    "tipoProceso": "HIPOTECARIO",
    "vencimientoPagare": []
  },
  "deudor": {
    "tel": {
      "fijo": 7502262,
      "celular": 3204955563
    },
    "primerNombre": "ANA",
    "segundoNombre": "EMILCE",
    "primerApellido": "ROJAS",
    "segundoApellido": "SARMIENTO",
    "cedula": 20896387,
    "direccion": "CARRERA 32 # 18 - 31 SUR",
    "email": "jose_agudelo@juancarpas.edu.com"
  },
  "fecha": "2018-10-17T05:00:00.000Z",
  "idProcesos": [50655580],
  "idRegUltimaAct": 830631840,
  "llaveProceso": "11001400306120170079300",
  "nombre": "ANA EMILCE ROJAS SARMIENTO",
  "numero": 139,
  "procesos": [
    {
      "idProceso": 50655580,
      "idConexion": 259,
      "llaveProceso": "11001400306120170079300",
      "fechaProceso": "2017-08-24T05:00:00.000Z",
      "fechaUltimaActuacion": "2018-10-17T05:00:00.000Z",
      "despacho": "JUZGADO 061 CIVIL MUNICIPAL DE BOGOTÁ ",
      "departamento": "BOGOTÁ",
      "sujetosProcesales": "Demandante: BANCOLOMBIA S.A. | Demandado: MARIA VILLACAMPA AINSA | Demandado: ANA EMILCE ROJAS SARMIENTO ",
      "esPrivado": false,
      "cantFilas": -1,
      "juzgado": {
        "id": 61,
        "tipo": "JUZGADO 061 CIVIL MUNICIPAL DE BOGOTÁ",
        "url": "https://www.ramajudicial.gov.co/web/juzgado-61-civil-municipal-de-bogota"
      }
    }
  ],
  "revisado": true,
  "terminado": true,
  "tipoProceso": "HIPOTECARIO",
  "ultimaActuacion": {
    "idRegActuacion": 830631840,
    "llaveProceso": "11001400306120170079300",
    "consActuacion": 21,
    "fechaActuacion": "2018-10-17T05:00:00.000Z",
    "actuacion": "Archivo Definitivo",
    "anotacion": "347",
    "fechaInicial": null,
    "fechaFinal": null,
    "fechaRegistro": "2018-10-17T05:00:00.000Z",
    "codRegla": "00                              ",
    "conDocumentos": false,
    "cant": 21,
    "idProceso": 50655580,
    "isUltimaAct": true
  },
  "updatedAt": "2024-01-02T02:09:32.104Z"
}
