{
  "tipoConsulta": "NumeroRadicacion",
  "procesos": [
    {
      "idProceso": 51002530,
      "idConexion": 259,
      "llaveProceso": "11001400302420180014300",
      "fechaProceso": "2018-02-12T00:00:00",
      "fechaUltimaActuacion": "2019-09-27T00:00:00",
      "despacho": "JUZGADO 024 CIVIL MUNICIPAL DE BOGOTÁ ",
      "departamento": "BOGOTÁ",
      "sujetosProcesales": "Demandante: BANCOLOMBIA S.A. | Demandado: MARTHA ANDREA MORA COLLAZOS ",
      "esPrivado": false,
      "cantFilas": -1
    }
  ],
  "parametros": {
    "numero": "11001400302420180014300",
    "nombre": null,
    "tipoPersona": null,
    "idSujeto": null,
    "ponente": null,
    "claseProceso": null,
    "codificacionDespacho": null,
    "soloActivos": false
  },
  "paginacion": {
    "cantidadRegistros": 1,
    "registrosPagina": 20,
    "cantidadPaginas": 1,
    "pagina": 1,
    "paginas": null
  }
}
