{
  "id": 38261511,
  "actuaciones": [
    {
      "idRegActuacion": 265448180,
      "llaveProceso": "11001400306420170113800",
      "consActuacion": 10,
      "fechaActuacion": "2018-04-25T05:00:00.000Z",
      "actuacion": "Retiro de demanada",
      "anotacion": "RETIRA DEMANDA DIANA TRIANA SUAREZ AUTORIZADA, SIN COMPENSACION",
      "fechaInicial": null,
      "fechaFinal": null,
      "fechaRegistro": "2018-04-25T05:00:00.000Z",
      "codRegla": "00                              ",
      "conDocumentos": false,
      "cant": 10,
      "idProceso": 17941680,
      "isUltimaAct": true,
      "createdAt": "2024-02-10T00:54:25.117Z"
    },
    {
      "idRegActuacion": 265448170,
      "llaveProceso": "11001400306420170113800",
      "consActuacion": 9,
      "fechaActuacion": "2017-10-05T05:00:00.000Z",
      "actuacion": "Fijacion estado",
      "anotacion": "Actuación registrada el 05/10/2017 a las 09:21:15.",
      "fechaInicial": "2017-10-06T05:00:00.000Z",
      "fechaFinal": "2017-10-06T05:00:00.000Z",
      "fechaRegistro": "2017-10-05T05:00:00.000Z",
      "codRegla": "00                              ",
      "conDocumentos": false,
      "cant": 10,
      "idProceso": 17941680,
      "isUltimaAct": false,
      "createdAt": "2024-02-10T00:54:25.117Z"
    },
    {
      "idRegActuacion": 265448160,
      "llaveProceso": "11001400306420170113800",
      "consActuacion": 8,
      "fechaActuacion": "2017-10-05T05:00:00.000Z",
      "actuacion": "Auto de Trámite",
      "anotacion": null,
      "fechaInicial": null,
      "fechaFinal": null,
      "fechaRegistro": "2017-10-05T05:00:00.000Z",
      "codRegla": "00                              ",
      "conDocumentos": false,
      "cant": 10,
      "idProceso": 17941680,
      "isUltimaAct": false,
      "createdAt": "2024-02-10T00:54:25.117Z"
    },
    {
      "idRegActuacion": 265448150,
      "llaveProceso": "11001400306420170113800",
      "consActuacion": 7,
      "fechaActuacion": "2017-09-29T05:00:00.000Z",
      "actuacion": "Al despacho",
      "anotacion": null,
      "fechaInicial": null,
      "fechaFinal": null,
      "fechaRegistro": "2017-09-29T05:00:00.000Z",
      "codRegla": "00                              ",
      "conDocumentos": false,
      "cant": 10,
      "idProceso": 17941680,
      "isUltimaAct": false,
      "createdAt": "2024-02-10T00:54:25.117Z"
    },
    {
      "idRegActuacion": 265448140,
      "llaveProceso": "11001400306420170113800",
      "consActuacion": 6,
      "fechaActuacion": "2017-09-12T05:00:00.000Z",
      "actuacion": "Comunicación secretarial firmada",
      "anotacion": null,
      "fechaInicial": null,
      "fechaFinal": null,
      "fechaRegistro": "2017-09-12T05:00:00.000Z",
      "codRegla": "00                              ",
      "conDocumentos": false,
      "cant": 10,
      "idProceso": 17941680,
      "isUltimaAct": false,
      "createdAt": "2024-02-10T00:54:25.117Z"
    },
    {
      "idRegActuacion": 265448130,
      "llaveProceso": "11001400306420170113800",
      "consActuacion": 5,
      "fechaActuacion": "2017-09-11T05:00:00.000Z",
      "actuacion": "Oficio Elaborado",
      "anotacion": "OFICIO No. 3396 REGISTRO",
      "fechaInicial": null,
      "fechaFinal": null,
      "fechaRegistro": "2017-09-11T05:00:00.000Z",
      "codRegla": "00                              ",
      "conDocumentos": false,
      "cant": 10,
      "idProceso": 17941680,
      "isUltimaAct": false,
      "createdAt": "2024-02-10T00:54:25.117Z"
    },
    {
      "idRegActuacion": 265448120,
      "llaveProceso": "11001400306420170113800",
      "consActuacion": 4,
      "fechaActuacion": "2017-08-25T05:00:00.000Z",
      "actuacion": "Fijacion estado",
      "anotacion": "Actuación registrada el 25/08/2017 a las 10:55:41.",
      "fechaInicial": "2017-08-28T05:00:00.000Z",
      "fechaFinal": "2017-08-28T05:00:00.000Z",
      "fechaRegistro": "2017-08-25T05:00:00.000Z",
      "codRegla": "00                              ",
      "conDocumentos": false,
      "cant": 10,
      "idProceso": 17941680,
      "isUltimaAct": false,
      "createdAt": "2024-02-10T00:54:25.117Z"
    },
    {
      "idRegActuacion": 265448110,
      "llaveProceso": "11001400306420170113800",
      "consActuacion": 3,
      "fechaActuacion": "2017-08-25T05:00:00.000Z",
      "actuacion": "Auto libra mandamiento ejecutivo",
      "anotacion": null,
      "fechaInicial": null,
      "fechaFinal": null,
      "fechaRegistro": "2017-08-25T05:00:00.000Z",
      "codRegla": "00                              ",
      "conDocumentos": false,
      "cant": 10,
      "idProceso": 17941680,
      "isUltimaAct": false,
      "createdAt": "2024-02-10T00:54:25.117Z"
    },
    {
      "idRegActuacion": 265448100,
      "llaveProceso": "11001400306420170113800",
      "consActuacion": 2,
      "fechaActuacion": "2017-08-22T05:00:00.000Z",
      "actuacion": "Al despacho",
      "anotacion": null,
      "fechaInicial": null,
      "fechaFinal": null,
      "fechaRegistro": "2017-08-22T05:00:00.000Z",
      "codRegla": "00                              ",
      "conDocumentos": false,
      "cant": 10,
      "idProceso": 17941680,
      "isUltimaAct": false,
      "createdAt": "2024-02-10T00:54:25.117Z"
    },
    {
      "idRegActuacion": 265448090,
      "llaveProceso": "11001400306420170113800",
      "consActuacion": 1,
      "fechaActuacion": "2017-08-22T05:00:00.000Z",
      "actuacion": " Radicación de Proceso",
      "anotacion": "Actuación de  Radicación de Proceso  realizada el 22/08/2017 a las 07:32:30",
      "fechaInicial": "2017-08-22T05:00:00.000Z",
      "fechaFinal": "2017-08-22T05:00:00.000Z",
      "fechaRegistro": "2017-08-22T05:00:00.000Z",
      "codRegla": "00                              ",
      "conDocumentos": false,
      "cant": 10,
      "idProceso": 17941680,
      "isUltimaAct": false,
      "createdAt": "2024-02-10T00:54:25.117Z"
    }
  ],
  "category": "Terminados",
  "codeudor": {
    "nombre": null,
    "cedula": null,
    "direccion": null,
    "telefono": null,
    "id": 54
  },
  "demanda": {
    "liquidacion": "1000",
    "avaluo": "1000",
    "capitalAdeudado": "18400664.75",
    "departamento": "CUNDINAMARCA",
    "despacho": null,
    "entregaGarantiasAbogado": "1970-01-01T00:00:42.898Z",
    "etapaProcesal": "NOTIFICACION",
    "fechaPresentacion": ["1970-01-01T00:00:42.907Z"],
    "id": 54,
    "llaveProceso": "11001400306420170113800",
    "mandamientoPago": [],
    "municipio": "BOGOTA",
    "notificacion": {
      "id": 54,
      "notifiers": [
        {
          "tipo": "291",
          "fechaRecibido": "1970-01-01T00:00:42.972Z",
          "fechaAporta": null,
          "resultado": false
        },
        {
          "tipo": "292",
          "fechaRecibido": "3396-01-01T00:00:00.000Z",
          "fechaAporta": null,
          "resultado": false
        }
      ],
      "certimail": null,
      "fisico": null,
      "autoNotificado": null
    },
    "obligacion": ["320095437"],
    "radicado": "2017 - 01138",
    "tipoProceso": "HIPOTECARIO",
    "vencimientoPagare": ["1970-01-01T00:00:44.653Z"],
    "medidasCautelares": {
      "id": 54,
      "fechaOrdenaMedida": "2024-02-10T00:54:25.073Z",
      "medidaSolicitada": null
    }
  },
  "deudor": {
    "id": 54,
    "telCelular": "3138615288",
    "telFijo": null,
    "primerNombre": "OLGA",
    "segundoNombre": null,
    "primerApellido": "GALLEGO",
    "segundoApellido": null,
    "cedula": "38261511",
    "direccion": "CARRERA 87D No. 48-03 SUR//DIAGONAL 49 No. 85-79 SUR TORRE 10 APARTAMENTO 2",
    "email": "olgagallego63@hotmail.com"
  },
  "fecha": "2018-04-25T05:00:00.000Z",
  "idProcesos": [17941680],
  "idRegUltimaAct": 265448180,
  "llaveProceso": "11001400306420170113800",
  "nombre": "olga gallego",
  "numero": 54,
  "procesos": [
    {
      "idProceso": 17941680,
      "idConexion": 260,
      "llaveProceso": "11001400306420170113800",
      "fechaProceso": "2017-08-22T05:00:00.000Z",
      "fechaUltimaActuacion": "2018-04-25T05:00:00.000Z",
      "despacho": "JUZGADO 064 CIVIL MUNICIPAL DE BOGOTÁ ",
      "departamento": "BOGOTÁ",
      "sujetosProcesales": "Demandante: BANCOLOMBIA S.A. | Demandado: OLGA GALLEGO ",
      "esPrivado": false,
      "cantFilas": -1,
      "juzgado": {
        "id": 64,
        "tipo": "JUZGADO 064 CIVIL MUNICIPAL DE BOGOTÁ",
        "url": "https://www.ramajudicial.gov.co/web/juzgado-064-civil-municipal-de-bogota"
      }
    }
  ],
  "revisado": false,
  "terminado": true,
  "tipoProceso": "HIPOTECARIO",
  "ultimaActuacion": {
    "idRegActuacion": 265448180,
    "llaveProceso": "11001400306420170113800",
    "consActuacion": 10,
    "fechaActuacion": "2018-04-25T05:00:00.000Z",
    "actuacion": "Retiro de demanada",
    "anotacion": "RETIRA DEMANDA DIANA TRIANA SUAREZ AUTORIZADA, SIN COMPENSACION",
    "fechaInicial": null,
    "fechaFinal": null,
    "fechaRegistro": "2018-04-25T05:00:00.000Z",
    "codRegla": "00                              ",
    "conDocumentos": false,
    "cant": 10,
    "idProceso": 17941680,
    "isUltimaAct": true
  },
  "notas": [
    {
      "carpetaNumero": 54,
      "createdAt": "2024-02-10T00:54:25.073Z",
      "pathname": null,
      "dueDate": null,
      "text": "25 DE ABRIL DE 2018 SE RETIRO DEMANDA DEL JUZGADO SIN MEDIDAS DECRETADAS Y REGISTRADAS ",
      "content": []
    },
    {
      "carpetaNumero": 54,
      "createdAt": "2024-02-10T00:54:25.073Z",
      "pathname": null,
      "dueDate": null,
      "text": " EL 27 DE ABRIL DE 2018 SE DEVOLVIERON GARANTIAS A AECSA S.A.",
      "content": []
    }
  ],
  "updatedAt": "2024-02-10T00:54:25.074Z"
}
