{
  "id": 1012341563,
  "actuaciones": [
    {
      "idRegActuacion": 653663500,
      "llaveProceso": "11001400301620180057300",
      "consActuacion": 26,
      "fechaActuacion": "2019-09-16T05:00:00.000Z",
      "actuacion": "Archivo Definitivo",
      "anotacion": "TERMINADOS PAQUETE 444/2019 \r\n\r\n",
      "fechaInicial": null,
      "fechaFinal": null,
      "fechaRegistro": "2019-09-16T05:00:00.000Z",
      "codRegla": "00                              ",
      "conDocumentos": false,
      "cant": 26,
      "idProceso": 51205750,
      "isUltimaAct": true,
      "createdAt": "2024-01-02T02:11:15.962Z"
    },
    {
      "idRegActuacion": 653663490,
      "llaveProceso": "11001400301620180057300",
      "consActuacion": 25,
      "fechaActuacion": "2019-07-26T05:00:00.000Z",
      "actuacion": "Fijacion estado",
      "anotacion": "Actuación registrada el 26/07/2019 a las 10:41:19.",
      "fechaInicial": "2019-07-29T05:00:00.000Z",
      "fechaFinal": "2019-07-29T05:00:00.000Z",
      "fechaRegistro": "2019-07-26T05:00:00.000Z",
      "codRegla": "00                              ",
      "conDocumentos": false,
      "cant": 26,
      "idProceso": 51205750,
      "isUltimaAct": false,
      "createdAt": "2024-01-02T02:11:15.962Z"
    },
    {
      "idRegActuacion": 653663480,
      "llaveProceso": "11001400301620180057300",
      "consActuacion": 24,
      "fechaActuacion": "2019-07-26T05:00:00.000Z",
      "actuacion": "Auto resuelve renuncia poder",
      "anotacion": null,
      "fechaInicial": null,
      "fechaFinal": null,
      "fechaRegistro": "2019-07-26T05:00:00.000Z",
      "codRegla": "00                              ",
      "conDocumentos": false,
      "cant": 26,
      "idProceso": 51205750,
      "isUltimaAct": false,
      "createdAt": "2024-01-02T02:11:15.962Z"
    },
    {
      "idRegActuacion": 653663470,
      "llaveProceso": "11001400301620180057300",
      "consActuacion": 23,
      "fechaActuacion": "2019-07-23T05:00:00.000Z",
      "actuacion": "Al despacho",
      "anotacion": null,
      "fechaInicial": null,
      "fechaFinal": null,
      "fechaRegistro": "2019-07-23T05:00:00.000Z",
      "codRegla": "00                              ",
      "conDocumentos": false,
      "cant": 26,
      "idProceso": 51205750,
      "isUltimaAct": false,
      "createdAt": "2024-01-02T02:11:15.962Z"
    },
    {
      "idRegActuacion": 653663460,
      "llaveProceso": "11001400301620180057300",
      "consActuacion": 22,
      "fechaActuacion": "2019-07-22T05:00:00.000Z",
      "actuacion": "Recepción memorial",
      "anotacion": "AUTORIZACIÓN ",
      "fechaInicial": null,
      "fechaFinal": null,
      "fechaRegistro": "2019-07-22T05:00:00.000Z",
      "codRegla": "00                              ",
      "conDocumentos": false,
      "cant": 26,
      "idProceso": 51205750,
      "isUltimaAct": false,
      "createdAt": "2024-01-02T02:11:15.962Z"
    },
    {
      "idRegActuacion": 653663450,
      "llaveProceso": "11001400301620180057300",
      "consActuacion": 21,
      "fechaActuacion": "2019-07-12T05:00:00.000Z",
      "actuacion": "Desarchivado",
      "anotacion": "Se encuentra en la secretaría de este Despacho Judicial, a disposición de la parte interesada para los fines legales pertinentes\r\n   \r\n",
      "fechaInicial": null,
      "fechaFinal": null,
      "fechaRegistro": "2019-07-12T05:00:00.000Z",
      "codRegla": "00                              ",
      "conDocumentos": false,
      "cant": 26,
      "idProceso": 51205750,
      "isUltimaAct": false,
      "createdAt": "2024-01-02T02:11:15.962Z"
    },
    {
      "idRegActuacion": 653663440,
      "llaveProceso": "11001400301620180057300",
      "consActuacion": 20,
      "fechaActuacion": "2019-04-12T05:00:00.000Z",
      "actuacion": "Archivo Definitivo",
      "anotacion": "ARCHIVADO PAQUETE 403 DEE 2018",
      "fechaInicial": null,
      "fechaFinal": null,
      "fechaRegistro": "2019-04-12T05:00:00.000Z",
      "codRegla": "00                              ",
      "conDocumentos": false,
      "cant": 26,
      "idProceso": 51205750,
      "isUltimaAct": false,
      "createdAt": "2024-01-02T02:11:15.962Z"
    },
    {
      "idRegActuacion": 653663430,
      "llaveProceso": "11001400301620180057300",
      "consActuacion": 19,
      "fechaActuacion": "2018-10-19T05:00:00.000Z",
      "actuacion": "Oficio Elaborado",
      "anotacion": "OF. 3129 (DESEMBARGO) revisión y firma ",
      "fechaInicial": null,
      "fechaFinal": null,
      "fechaRegistro": "2018-10-19T05:00:00.000Z",
      "codRegla": "00                              ",
      "conDocumentos": false,
      "cant": 26,
      "idProceso": 51205750,
      "isUltimaAct": false,
      "createdAt": "2024-01-02T02:11:15.962Z"
    },
    {
      "idRegActuacion": 653663420,
      "llaveProceso": "11001400301620180057300",
      "consActuacion": 18,
      "fechaActuacion": "2018-10-11T05:00:00.000Z",
      "actuacion": "Fijacion estado",
      "anotacion": "Actuación registrada el 11/10/2018 a las 15:14:29.",
      "fechaInicial": "2018-10-12T05:00:00.000Z",
      "fechaFinal": "2018-10-12T05:00:00.000Z",
      "fechaRegistro": "2018-10-11T05:00:00.000Z",
      "codRegla": "00                              ",
      "conDocumentos": false,
      "cant": 26,
      "idProceso": 51205750,
      "isUltimaAct": false,
      "createdAt": "2024-01-02T02:11:15.962Z"
    },
    {
      "idRegActuacion": 653663410,
      "llaveProceso": "11001400301620180057300",
      "consActuacion": 17,
      "fechaActuacion": "2018-10-11T05:00:00.000Z",
      "actuacion": "Auto termina proceso por Pago",
      "anotacion": null,
      "fechaInicial": null,
      "fechaFinal": null,
      "fechaRegistro": "2018-10-11T05:00:00.000Z",
      "codRegla": "00                              ",
      "conDocumentos": false,
      "cant": 26,
      "idProceso": 51205750,
      "isUltimaAct": false,
      "createdAt": "2024-01-02T02:11:15.962Z"
    },
    {
      "idRegActuacion": 653663400,
      "llaveProceso": "11001400301620180057300",
      "consActuacion": 16,
      "fechaActuacion": "2018-10-09T05:00:00.000Z",
      "actuacion": "Al despacho",
      "anotacion": null,
      "fechaInicial": null,
      "fechaFinal": null,
      "fechaRegistro": "2018-10-09T05:00:00.000Z",
      "codRegla": "00                              ",
      "conDocumentos": false,
      "cant": 26,
      "idProceso": 51205750,
      "isUltimaAct": false,
      "createdAt": "2024-01-02T02:11:15.962Z"
    },
    {
      "idRegActuacion": 653663390,
      "llaveProceso": "11001400301620180057300",
      "consActuacion": 15,
      "fechaActuacion": "2018-10-08T05:00:00.000Z",
      "actuacion": "Recepción memorial",
      "anotacion": "solicitan terminacion",
      "fechaInicial": null,
      "fechaFinal": null,
      "fechaRegistro": "2018-10-08T05:00:00.000Z",
      "codRegla": "00                              ",
      "conDocumentos": false,
      "cant": 26,
      "idProceso": 51205750,
      "isUltimaAct": false,
      "createdAt": "2024-01-02T02:11:15.962Z"
    },
    {
      "idRegActuacion": 653663380,
      "llaveProceso": "11001400301620180057300",
      "consActuacion": 14,
      "fechaActuacion": "2018-08-28T05:00:00.000Z",
      "actuacion": "Oficio Elaborado",
      "anotacion": "OF. 1766 (embargo)",
      "fechaInicial": null,
      "fechaFinal": null,
      "fechaRegistro": "2018-08-28T05:00:00.000Z",
      "codRegla": "00                              ",
      "conDocumentos": false,
      "cant": 26,
      "idProceso": 51205750,
      "isUltimaAct": false,
      "createdAt": "2024-01-02T02:11:15.962Z"
    },
    {
      "idRegActuacion": 653663370,
      "llaveProceso": "11001400301620180057300",
      "consActuacion": 13,
      "fechaActuacion": "2018-08-17T05:00:00.000Z",
      "actuacion": "Fijacion estado",
      "anotacion": "Actuación registrada el 17/08/2018 a las 15:13:10.",
      "fechaInicial": "2018-08-21T05:00:00.000Z",
      "fechaFinal": "2018-08-21T05:00:00.000Z",
      "fechaRegistro": "2018-08-17T05:00:00.000Z",
      "codRegla": "00                              ",
      "conDocumentos": false,
      "cant": 26,
      "idProceso": 51205750,
      "isUltimaAct": false,
      "createdAt": "2024-01-02T02:11:15.962Z"
    },
    {
      "idRegActuacion": 653663360,
      "llaveProceso": "11001400301620180057300",
      "consActuacion": 12,
      "fechaActuacion": "2018-08-17T05:00:00.000Z",
      "actuacion": "Auto resuelve corrección providencia",
      "anotacion": null,
      "fechaInicial": null,
      "fechaFinal": null,
      "fechaRegistro": "2018-08-17T05:00:00.000Z",
      "codRegla": "00                              ",
      "conDocumentos": false,
      "cant": 26,
      "idProceso": 51205750,
      "isUltimaAct": false,
      "createdAt": "2024-01-02T02:11:15.962Z"
    },
    {
      "idRegActuacion": 653663350,
      "llaveProceso": "11001400301620180057300",
      "consActuacion": 11,
      "fechaActuacion": "2018-08-08T05:00:00.000Z",
      "actuacion": "Al despacho",
      "anotacion": null,
      "fechaInicial": null,
      "fechaFinal": null,
      "fechaRegistro": "2018-08-08T05:00:00.000Z",
      "codRegla": "00                              ",
      "conDocumentos": false,
      "cant": 26,
      "idProceso": 51205750,
      "isUltimaAct": false,
      "createdAt": "2024-01-02T02:11:15.962Z"
    },
    {
      "idRegActuacion": 653663340,
      "llaveProceso": "11001400301620180057300",
      "consActuacion": 10,
      "fechaActuacion": "2018-08-06T05:00:00.000Z",
      "actuacion": "Oficio Elaborado",
      "anotacion": "OF. 1583 (EMBARGO) INGRESAR CON SOLICITUD CORRECCIÓN AUTO ",
      "fechaInicial": null,
      "fechaFinal": null,
      "fechaRegistro": "2018-08-06T05:00:00.000Z",
      "codRegla": "00                              ",
      "conDocumentos": false,
      "cant": 26,
      "idProceso": 51205750,
      "isUltimaAct": false,
      "createdAt": "2024-01-02T02:11:15.962Z"
    },
    {
      "idRegActuacion": 653663330,
      "llaveProceso": "11001400301620180057300",
      "consActuacion": 9,
      "fechaActuacion": "2018-07-26T05:00:00.000Z",
      "actuacion": "Recepción memorial",
      "anotacion": "ALLEGAN SOLICITUD DE CORRECCIÓN MANDAMIENTO DE PAGO",
      "fechaInicial": null,
      "fechaFinal": null,
      "fechaRegistro": "2018-07-26T05:00:00.000Z",
      "codRegla": "00                              ",
      "conDocumentos": false,
      "cant": 26,
      "idProceso": 51205750,
      "isUltimaAct": false,
      "createdAt": "2024-01-02T02:11:15.962Z"
    },
    {
      "idRegActuacion": 653663320,
      "llaveProceso": "11001400301620180057300",
      "consActuacion": 8,
      "fechaActuacion": "2018-07-19T05:00:00.000Z",
      "actuacion": "Fijacion estado",
      "anotacion": "Actuación registrada el 19/07/2018 a las 11:44:17.",
      "fechaInicial": "2018-07-23T05:00:00.000Z",
      "fechaFinal": "2018-07-23T05:00:00.000Z",
      "fechaRegistro": "2018-07-19T05:00:00.000Z",
      "codRegla": "00                              ",
      "conDocumentos": false,
      "cant": 26,
      "idProceso": 51205750,
      "isUltimaAct": false,
      "createdAt": "2024-01-02T02:11:15.962Z"
    },
    {
      "idRegActuacion": 653663310,
      "llaveProceso": "11001400301620180057300",
      "consActuacion": 7,
      "fechaActuacion": "2018-07-19T05:00:00.000Z",
      "actuacion": "Auto libra mandamiento ejecutivo",
      "anotacion": null,
      "fechaInicial": null,
      "fechaFinal": null,
      "fechaRegistro": "2018-07-19T05:00:00.000Z",
      "codRegla": "00                              ",
      "conDocumentos": false,
      "cant": 26,
      "idProceso": 51205750,
      "isUltimaAct": false,
      "createdAt": "2024-01-02T02:11:15.962Z"
    },
    {
      "idRegActuacion": 653663300,
      "llaveProceso": "11001400301620180057300",
      "consActuacion": 6,
      "fechaActuacion": "2018-06-12T05:00:00.000Z",
      "actuacion": "Al despacho",
      "anotacion": null,
      "fechaInicial": null,
      "fechaFinal": null,
      "fechaRegistro": "2018-06-12T05:00:00.000Z",
      "codRegla": "00                              ",
      "conDocumentos": false,
      "cant": 26,
      "idProceso": 51205750,
      "isUltimaAct": false,
      "createdAt": "2024-01-02T02:11:15.962Z"
    },
    {
      "idRegActuacion": 653663290,
      "llaveProceso": "11001400301620180057300",
      "consActuacion": 5,
      "fechaActuacion": "2018-06-07T05:00:00.000Z",
      "actuacion": "Recepción memorial",
      "anotacion": "SUBSANACIÓN DEMANDA (luz)",
      "fechaInicial": null,
      "fechaFinal": null,
      "fechaRegistro": "2018-06-07T05:00:00.000Z",
      "codRegla": "00                              ",
      "conDocumentos": false,
      "cant": 26,
      "idProceso": 51205750,
      "isUltimaAct": false,
      "createdAt": "2024-01-02T02:11:15.962Z"
    },
    {
      "idRegActuacion": 653663280,
      "llaveProceso": "11001400301620180057300",
      "consActuacion": 4,
      "fechaActuacion": "2018-05-29T05:00:00.000Z",
      "actuacion": "Fijacion estado",
      "anotacion": "Actuación registrada el 29/05/2018 a las 15:39:43.",
      "fechaInicial": "2018-05-30T05:00:00.000Z",
      "fechaFinal": "2018-05-30T05:00:00.000Z",
      "fechaRegistro": "2018-05-29T05:00:00.000Z",
      "codRegla": "00                              ",
      "conDocumentos": false,
      "cant": 26,
      "idProceso": 51205750,
      "isUltimaAct": false,
      "createdAt": "2024-01-02T02:11:15.962Z"
    },
    {
      "idRegActuacion": 653663270,
      "llaveProceso": "11001400301620180057300",
      "consActuacion": 3,
      "fechaActuacion": "2018-05-29T05:00:00.000Z",
      "actuacion": "Auto inadmite demanda",
      "anotacion": null,
      "fechaInicial": null,
      "fechaFinal": null,
      "fechaRegistro": "2018-05-29T05:00:00.000Z",
      "codRegla": "00                              ",
      "conDocumentos": false,
      "cant": 26,
      "idProceso": 51205750,
      "isUltimaAct": false,
      "createdAt": "2024-01-02T02:11:15.962Z"
    },
    {
      "idRegActuacion": 653663260,
      "llaveProceso": "11001400301620180057300",
      "consActuacion": 2,
      "fechaActuacion": "2018-05-24T05:00:00.000Z",
      "actuacion": "Al despacho",
      "anotacion": null,
      "fechaInicial": null,
      "fechaFinal": null,
      "fechaRegistro": "2018-05-24T05:00:00.000Z",
      "codRegla": "00                              ",
      "conDocumentos": false,
      "cant": 26,
      "idProceso": 51205750,
      "isUltimaAct": false,
      "createdAt": "2024-01-02T02:11:15.962Z"
    },
    {
      "idRegActuacion": 653663250,
      "llaveProceso": "11001400301620180057300",
      "consActuacion": 1,
      "fechaActuacion": "2018-05-23T05:00:00.000Z",
      "actuacion": " Radicación de Proceso",
      "anotacion": "Actuación de  Radicación de Proceso  realizada el 23/05/2018 a las 16:36:57",
      "fechaInicial": "2018-05-23T05:00:00.000Z",
      "fechaFinal": "2018-05-23T05:00:00.000Z",
      "fechaRegistro": "2018-05-23T05:00:00.000Z",
      "codRegla": "00                              ",
      "conDocumentos": false,
      "cant": 26,
      "idProceso": 51205750,
      "isUltimaAct": false,
      "createdAt": "2024-01-02T02:11:15.962Z"
    }
  ],
  "category": "Terminados",
  "codeudor": null,
  "demanda": {
    "obligacion": ["20990131392"],
    "llaveProceso": "11001400301620180057300",
    "notificacion": null,
    "medidasCautelares": null,
    "capitalAdeudado": 32124573,
    "departamento": "CUNDINAMARCA",
    "despacho": null,
    "entregaGarantiasAbogado": null,
    "etapaProcesal": "ADMISION",
    "fechaPresentacion": ["2018-05-22T05:00:00.000Z"],
    "mandamientoPago": null,
    "municipio": "BOGOTA",
    "radicado": "2018 - 00573",
    "tipoProceso": "HIPOTECARIO",
    "vencimientoPagare": ["2025-08-18T05:00:00.000Z"]
  },
  "deudor": {
    "tel": {
      "fijo": null,
      "celular": null
    },
    "primerNombre": "MARIBEL",
    "segundoNombre": "REVELO",
    "primerApellido": "QUIROGA",
    "segundoApellido": null,
    "cedula": 1012341563,
    "direccion": "CALLE 62A SUR-No 73C-21 T 1 APTO 202",
    "email": "marysqs@hotmail.com"
  },
  "fecha": "2019-09-16T05:00:00.000Z",
  "idProcesos": [51205750],
  "idRegUltimaAct": 653663500,
  "llaveProceso": "11001400301620180057300",
  "nombre": "MARIBEL REVELO QUIROGA",
  "numero": 435,
  "procesos": [
    {
      "idProceso": 51205750,
      "idConexion": 259,
      "llaveProceso": "11001400301620180057300",
      "fechaProceso": "2018-05-23T05:00:00.000Z",
      "fechaUltimaActuacion": "2019-09-16T05:00:00.000Z",
      "despacho": "JUZGADO 016 CIVIL MUNICIPAL DE BOGOTÁ ",
      "departamento": "BOGOTÁ",
      "sujetosProcesales": "Demandante: BANCOLOMBIA  S.A. | Demandado: MARIBEL RAVELO QUIROGA ",
      "esPrivado": false,
      "cantFilas": -1,
      "juzgado": {
        "id": 16,
        "tipo": "JUZGADO 016 CIVIL MUNICIPAL DE BOGOTÁ",
        "url": "https://www.ramajudicial.gov.co/web/juzgado-016-civil-municipal-de-bogota"
      }
    }
  ],
  "revisado": true,
  "terminado": true,
  "tipoProceso": "HIPOTECARIO",
  "ultimaActuacion": {
    "idRegActuacion": 653663500,
    "llaveProceso": "11001400301620180057300",
    "consActuacion": 26,
    "fechaActuacion": "2019-09-16T05:00:00.000Z",
    "actuacion": "Archivo Definitivo",
    "anotacion": "TERMINADOS PAQUETE 444/2019 \r\n\r\n",
    "fechaInicial": null,
    "fechaFinal": null,
    "fechaRegistro": "2019-09-16T05:00:00.000Z",
    "codRegla": "00                              ",
    "conDocumentos": false,
    "cant": 26,
    "idProceso": 51205750,
    "isUltimaAct": true
  },
  "updatedAt": "2024-01-02T02:11:15.689Z"
}
